smhi/__init__.py
smhi/smhi_lib.py
smhi/test_smhi_lib.py
smhi_pkg-1.0.19.dist-info/LICENSE
smhi_pkg-1.0.19.dist-info/METADATA
smhi_pkg-1.0.19.dist-info/WHEEL
smhi_pkg-1.0.19.dist-info/top_level.txt
smhi_pkg-1.0.19.dist-info/RECORD
