Metadata-Version: 2.2
Name: smhi_pkg
Version: 1.0.19
Summary: Gets the weather forecast data from Swedish weather institute
Home-page: https://github.com/joysoftware/pypi_smhi
Author: helto4real
Author-email: info@joysoftware.org
License: MIT
Classifier: Programming Language :: Python :: 3
Classifier: License :: OSI Approved :: MIT License
Classifier: Operating System :: OS Independent
Classifier: Development Status :: 4 - Beta
License-File: LICENSE
Dynamic: author
Dynamic: author-email
Dynamic: classifier
Dynamic: description
Dynamic: description-content-type
Dynamic: home-page
Dynamic: license
Dynamic: summary
